fletplus/__init__.py
fletplus/core.py
fletplus/animation/__init__.py
fletplus/animation/controller.py
fletplus/animation/listeners_rs.py
fletplus/animation/wrappers.py
fletplus/animation/listeners_pr_rs/Cargo.lock
fletplus/animation/listeners_pr_rs/Cargo.toml
fletplus/animation/listeners_pr_rs/__init__.py
fletplus/animation/listeners_pr_rs/src/lib.rs
fletplus/cli/__init__.py
fletplus/cli/build.py
fletplus/cli/main.py
fletplus/cli/templates/app/src/__init__.py
fletplus/cli/templates/app/src/main.py
fletplus/components/__init__.py
fletplus/components/accessibility_panel.py
fletplus/components/adaptive_app_header.py
fletplus/components/adaptive_layout.py
fletplus/components/buttons.py
fletplus/components/caption_overlay.py
fletplus/components/command_palette.py
fletplus/components/layouts.py
fletplus/components/responsive_container.py
fletplus/components/responsive_grid.py
fletplus/components/sidebar_admin.py
fletplus/components/smart_table.py
fletplus/components/universal_scaffold.py
fletplus/components/charts/__init__.py
fletplus/components/charts/line_chart.py
fletplus/components/charts/line_chart_rs/Cargo.lock
fletplus/components/charts/line_chart_rs/Cargo.toml
fletplus/components/charts/line_chart_rs/__init__.py
fletplus/components/charts/line_chart_rs/src/lib.rs
fletplus/components/command_palette_rs/Cargo.lock
fletplus/components/command_palette_rs/Cargo.toml
fletplus/components/command_palette_rs/__init__.py
fletplus/components/command_palette_rs/src/lib.rs
fletplus/components/responsive_grid_rs/Cargo.lock
fletplus/components/responsive_grid_rs/Cargo.toml
fletplus/components/responsive_grid_rs/__init__.py
fletplus/components/responsive_grid_rs/src/lib.rs
fletplus/components/smart_table_rs/Cargo.lock
fletplus/components/smart_table_rs/Cargo.toml
fletplus/components/smart_table_rs/__init__.py
fletplus/components/smart_table_rs/src/lib.rs
fletplus/context/__init__.py
fletplus/desktop/__init__.py
fletplus/desktop/notifications.py
fletplus/desktop/system_tray.py
fletplus-0.2.9.dist-info/licenses/LICENSE.md
fletplus-0.2.9.dist-info/METADATA
fletplus-0.2.9.dist-info/WHEEL
fletplus-0.2.9.dist-info/entry_points.txt
fletplus-0.2.9.dist-info/top_level.txt
fletplus-0.2.9.dist-info/RECORD
