Metadata-Version: 2.4
Name: fletplus
Version: 0.2.9
Summary: Componentes visuales avanzados y herramientas mejoradas para Flet en Python.
Author-email: Adolfo González <adolfogonzal@gmail.com>
License: MIT
Project-URL: Homepage, https://github.com/Alphonsus411/fletplus
Project-URL: Source, https://github.com/Alphonsus411/fletplus
Project-URL: Documentation, https://github.com/Alphonsus411/fletplus#readme
Requires-Python: >=3.9
License-File: LICENSE.md
Requires-Dist: flet>=0.27.0
Requires-Dist: click>=8.1
Requires-Dist: watchdog>=3.0
Requires-Dist: websockets>=12.0
Requires-Dist: httpx>=0.28
Provides-Extra: speedups
Requires-Dist: cython>=3.0; extra == "speedups"
Provides-Extra: rust
Requires-Dist: pyrust-native>=0.0.2; extra == "rust"
Requires-Dist: maturin>=1.7; extra == "rust"
Provides-Extra: dev
Requires-Dist: pytest<9,>=7.4; extra == "dev"
Requires-Dist: ruff<1,>=0.5; extra == "dev"
Requires-Dist: black<25,>=24.0; extra == "dev"
Requires-Dist: mypy<2,>=1.7; extra == "dev"
Provides-Extra: qa
Requires-Dist: bandit<2,>=1.7.8; extra == "qa"
Requires-Dist: pip-audit<3,>=2.7; extra == "qa"
Requires-Dist: safety<3,>=2.3; extra == "qa"
Dynamic: license-file
